{
  "meta": {
    "stableOrder": true
  },
  "lockfileVersion": 3,
  "ATTENTION": "THIS IS AN AUTOGENERATED FILE. DO NOT EDIT THIS FILE DIRECTLY.",
  "specifiers": {
    "lib_neuro_router_core@../lib_neuro_router_core": "lib_neuro_router_core@../lib_neuro_router_core",
    "module_home@../module_home": "module_home@../module_home",
    "module_me@../module_me": "module_me@../module_me"
  },
  "packages": {
    "lib_neuro_router_core@../lib_neuro_router_core": {
      "name": "lib_neuro_router_core",
      "version": "1.0.0",
      "resolved": "../lib_neuro_router_core",
      "registryType": "local"
    },
    "module_home@../module_home": {
      "name": "module_home",
      "version": "1.0.0",
      "resolved": "../module_home",
      "registryType": "local",
      "dependencies": {
        "lib_neuro_router_core": "file:../lib_neuro_router_core"
      }
    },
    "module_me@../module_me": {
      "name": "module_me",
      "version": "1.0.0",
      "resolved": "../module_me",
      "registryType": "local",
      "dependencies": {
        "lib_neuro_router_core": "file:../lib_neuro_router_core"
      }
    }
  }
}